.gitignore
.gitlab-ci.yml
CHANGELOG.md
LICENSE.txt
README.md
pyproject.toml
setup.py
.gitlab/build.yml
.gitlab/defaults.yml
.gitlab/docs.yml
.gitlab/publish.yml
.gitlab/tests.yml
.gitlab/verify.yml
agox/__init__.py
agox/module.py
agox.egg-info/PKG-INFO
agox.egg-info/SOURCES.txt
agox.egg-info/dependency_links.txt
agox.egg-info/entry_points.txt
agox.egg-info/requires.txt
agox.egg-info/top_level.txt
agox/acquisitors/ABC_acquisitor.py
agox/acquisitors/EI.py
agox/acquisitors/GFE_aquisitor.py
agox/acquisitors/LCB.py
agox/acquisitors/LCB_penalty.py
agox/acquisitors/LCB_power.py
agox/acquisitors/__init__.py
agox/acquisitors/meta_acquisitor.py
agox/acquisitors/replica_exchange/__init__.py
agox/acquisitors/replica_exchange/default.py
agox/analysis/__init__.py
agox/analysis/search_analysis.py
agox/analysis/search_data.py
agox/analysis/criterion/__init__.py
agox/analysis/criterion/distance.py
agox/analysis/criterion/threshold.py
agox/analysis/criterion/base_criterion/__init__.py
agox/analysis/criterion/base_criterion/base_criterion.py
agox/analysis/criterion/base_criterion/discrete_distribution.py
agox/analysis/plot/__init__.py
agox/analysis/plot/property_plot.py
agox/analysis/plot/success_plot.py
agox/analysis/property/__init__.py
agox/analysis/property/descriptor_property.py
agox/analysis/property/energy.py
agox/analysis/property/free_energy.py
agox/analysis/property/property.py
agox/candidates/ABC_candidate.py
agox/candidates/__init__.py
agox/candidates/standard.py
agox/cli/__init__.py
agox/cli/cli_analysis.py
agox/cli/cli_convert.py
agox/cli/cli_graph_sorting.py
agox/cli/cli_notebook.py
agox/cli/cli_plot.py
agox/cli/main.py
agox/collectors/ABC_collector.py
agox/collectors/__init__.py
agox/collectors/ray_collector.py
agox/collectors/replica_exchange.py
agox/collectors/standard.py
agox/databases/ABC_database.py
agox/databases/__init__.py
agox/databases/concurrent_ordered.py
agox/databases/database.py
agox/databases/database_concurrent.py
agox/databases/database_utilities.py
agox/environments/ABC_environment.py
agox/environments/__init__.py
agox/environments/environment.py
agox/evaluators/ABC_evaluator.py
agox/evaluators/__init__.py
