Metadata-Version: 2.4
Name: agox
Version: 3.11.0
Summary: Atomistic Global Optimziation X is a framework for structure optimization in materials science.
Author: AGOX Developers
Author-email: "Mads-Peter V. Christiansen" <machri@phys.au.dk>, Nikolaj Rønne <nronne@phys.au.dk>, Bjørk Hammer <hammer@phys.au.dk>
License-Expression: GPL-3.0-only
Project-URL: homepage, https://agox.gitlab.io/agox/
Project-URL: Repository, https://gitlab.com/agox/agox
Classifier: Development Status :: 5 - Production/Stable
Classifier: Intended Audience :: Science/Research
Classifier: Operating System :: OS Independent
Classifier: Programming Language :: Python :: 3.10
Classifier: Programming Language :: Python :: 3.11
Classifier: Programming Language :: Python :: 3.12
Requires-Python: >=3.10
License-File: LICENSE.txt
Requires-Dist: numpy<2
Requires-Dist: scipy
Requires-Dist: ase
Requires-Dist: matplotlib
Requires-Dist: cymem
Requires-Dist: scikit-learn
Requires-Dist: h5py
Requires-Dist: matscipy
Requires-Dist: importlib-resources>1.3; python_version < "3.9"
Requires-Dist: dscribe>=2.0.0
Requires-Dist: nbformat
Requires-Dist: typing_extensions
Requires-Dist: ray
Requires-Dist: rich-click>=1.8.3
Provides-Extra: test
Requires-Dist: pytest; extra == "test"
Requires-Dist: pytest-mock; extra == "test"
Provides-Extra: docs
Requires-Dist: sphinx; extra == "docs"
Requires-Dist: furo; extra == "docs"
Requires-Dist: sphinx-autoapi; extra == "docs"
Requires-Dist: sphinx-copybutton; extra == "docs"
Requires-Dist: sphinx-tabs; extra == "docs"
Requires-Dist: sphinx-design; extra == "docs"
Provides-Extra: torchjax
Requires-Dist: torch; extra == "torchjax"
Requires-Dist: jax; extra == "torchjax"
Requires-Dist: jaxlib; extra == "torchjax"
Provides-Extra: all
Requires-Dist: agox[docs,test]; extra == "all"
Dynamic: license-file
